configs/.gptignore
configs/config.yml
configs/plugins/example.py
configs/plugins/print_hello_world.yml
configs/promts/role.analyst.md
configs/promts/role.analyst_v2.md
configs/promts/role.common.md
configs/promts/role.developer.md
configs/promts/role.developer_v2.md
configs/promts/role.reviewer.md
morix/__init__.py
morix/complection.py
morix/conversation.py
morix/helpers.py
morix/keys.py
morix/main.py
morix/plugin_loader.py
morix/run_functions.py
morix/scan.py
morix/settings.py
morix/version.py
morix/functions/__init__.py
morix/functions/execute_shell_command.py
morix/functions/file_operations.py
morix/functions/functions.yml
morix/functions/report_task_status.py
morix/plugins/__init__.py
morix/plugins/plugin_interface.py
morix-0.8.1.dist-info/LICENSE
morix-0.8.1.dist-info/METADATA
morix-0.8.1.dist-info/WHEEL
morix-0.8.1.dist-info/entry_points.txt
morix-0.8.1.dist-info/top_level.txt
morix-0.8.1.dist-info/RECORD
