Metadata-Version: 2.2
Name: morix
Version: 0.8.1
Home-page: https://gitlab.com/good-day-inc/morix/
Author: Kirill Kusov
Author-email: dzenkir@gmail.com
Classifier: Programming Language :: Python :: 3
Classifier: License :: OSI Approved :: MIT License
Classifier: Operating System :: OS Independent
Requires-Python: >=3.10
License-File: LICENSE
Requires-Dist: rich
Requires-Dist: prompt_toolkit
Requires-Dist: openai
Requires-Dist: pyyaml
Requires-Dist: colorama
Requires-Dist: tiktoken
Requires-Dist: typer
Requires-Dist: langchain_openai
Dynamic: author
Dynamic: author-email
Dynamic: classifier
Dynamic: description
Dynamic: description-content-type
Dynamic: home-page
Dynamic: requires-dist
Dynamic: requires-python
